gmail_api_wrapper/__init__.py
gmail_api_wrapper/connection.py
gmail_api_wrapper/utils.py
gmail_api_wrapper/version.py
gmail_api_wrapper/crud/__init__.py
gmail_api_wrapper/crud/modify.py
gmail_api_wrapper/crud/read.py
gmail_api_wrapper/crud/write.py
gmail_api_wrapper-0.1.1a2.dist-info/DESCRIPTION.rst
gmail_api_wrapper-0.1.1a2.dist-info/METADATA
gmail_api_wrapper-0.1.1a2.dist-info/RECORD
gmail_api_wrapper-0.1.1a2.dist-info/WHEEL
gmail_api_wrapper-0.1.1a2.dist-info/metadata.json
gmail_api_wrapper-0.1.1a2.dist-info/top_level.txt
tests/crud/__init__.py
tests/crud/test_modify.py
tests/crud/test_read.py
tests/crud/test_write.py
