Metadata-Version: 2.0
Name: gmail-api-wrapper
Version: 0.1.1a2
Summary: Gmail API Wrapper - Python Client
Home-page: https://github.com/yoda-yoda/gmail-api-wrapper/
Author: Denis Karanja
Author-email: dee.caranja@gmail.com
License: MIT
Keywords: gmail-api-wrapper,gmail python client
Platform: UNKNOWN
Classifier: Development Status :: 3 - Alpha
Classifier: Intended Audience :: Developers
Classifier: Topic :: Software Development :: Build Tools
Classifier: License :: OSI Approved :: MIT License
Classifier: Programming Language :: Python :: 2.7
Classifier: Programming Language :: Python :: 3
Classifier: Programming Language :: Python :: 3.2
Classifier: Programming Language :: Python :: 3.3
Classifier: Programming Language :: Python :: 3.4
Classifier: Programming Language :: Python :: 3.5
Classifier: Programming Language :: Python :: 3.6
Requires-Dist: google-api-python-client (==1.6.3)
Requires-Dist: python-dateutil
